dogpile/__init__.py
dogpile/core.py
dogpile/lock.py
dogpile/py.typed
dogpile/cache/__init__.py
dogpile/cache/api.py
dogpile/cache/exception.py
dogpile/cache/proxy.py
dogpile/cache/region.py
dogpile/cache/util.py
dogpile/cache/backends/__init__.py
dogpile/cache/backends/file.py
dogpile/cache/backends/memcached.py
dogpile/cache/backends/memory.py
dogpile/cache/backends/null.py
dogpile/cache/backends/redis.py
dogpile/cache/plugins/__init__.py
dogpile/cache/plugins/mako_cache.py
dogpile/testing/__init__.py
dogpile/testing/assertions.py
dogpile/testing/fixtures.py
dogpile/util/__init__.py
dogpile/util/compat.py
dogpile/util/langhelpers.py
dogpile/util/nameregistry.py
dogpile/util/readwrite_lock.py
dogpile/util/typing.py
dogpile.cache-1.3.3.dist-info/LICENSE
dogpile.cache-1.3.3.dist-info/METADATA
dogpile.cache-1.3.3.dist-info/WHEEL
dogpile.cache-1.3.3.dist-info/entry_points.txt
dogpile.cache-1.3.3.dist-info/top_level.txt
dogpile.cache-1.3.3.dist-info/RECORD
