Metadata-Version: 2.1
Name: dogpile.cache
Version: 1.3.3
Summary: A caching front-end based on the Dogpile lock.
Author-email: Mike Bayer <mike_mp@zzzcomputing.com>
License: MIT
Project-URL: Homepage, https://github.com/sqlalchemy/dogpile.cache
Project-URL: Documentation, https://dogpilecache.sqlalchemy.org
Project-URL: Issue Tracker, https://github.com/sqlalchemy/dogpile.cache/
Keywords: caching
Classifier: Development Status :: 5 - Production/Stable
Classifier: Intended Audience :: Developers
Classifier: License :: OSI Approved :: MIT License
Classifier: Programming Language :: Python
Classifier: Programming Language :: Python :: 3
Requires-Python: >=3.8
License-File: LICENSE
Requires-Dist: decorator>=4.0.0
Requires-Dist: stevedore>=3.0.0
Requires-Dist: typing_extensions>=4.0.1; python_version < "3.11"
Provides-Extra: pifpaf
Requires-Dist: pifpaf>=2.5.0; extra == "pifpaf"
Requires-Dist: setuptools; python_version >= "3.12" and extra == "pifpaf"
